dual_attention/__init__.py
dual_attention/attention.py
dual_attention/attention_utils.py
dual_attention/dual_attention.py
dual_attention/dual_attn_blocks.py
dual_attention/hf.py
dual_attention/language_models.py
dual_attention/model_utils.py
dual_attention/positional_encoding.py
dual_attention/relational_attention.py
dual_attention/seq2seq_models.py
dual_attention/symbol_retrieval.py
dual_attention/transformer_blocks.py
dual_attention/vision_models.py
dual_attention/model_analysis/__init__.py
dual_attention/model_analysis/datlm_utils.py
dual_attention/model_analysis/lm_inference_app.py
dual_attention/model_analysis/lm_visualization_app.py
dual_attention-0.0.7.dist-info/LICENSE
dual_attention-0.0.7.dist-info/METADATA
dual_attention-0.0.7.dist-info/WHEEL
dual_attention-0.0.7.dist-info/top_level.txt
dual_attention-0.0.7.dist-info/RECORD
