Metadata-Version: 2.1
Name: dual_attention
Version: 0.0.7
Summary: Python package implementing the Dual Attention Transformer (DAT), as proposed by the paper "Disentangling and Integrating Relational and Sensory Information in Transformer Architectures" by Awni Altabaa, John Lafferty.
Author: Awni Altabaa
Author-email: awni.altabaa@yale.edu
License: MIT
Project-URL: Documentation, https://dual-attention-transformer.readthedocs.io/
Project-URL: Source, https://github.com/Awni00/dual-attention
Project-URL: Tracker, https://github.com/Awni00/dual-attention/issues
Classifier: Programming Language :: Python :: 3
Classifier: License :: OSI Approved :: MIT License
Classifier: Operating System :: OS Independent
License-File: LICENSE
Requires-Dist: einops
